[{"components":[{"content":{"parent":200,"pos":{"r":0.999904509459936,"x":-11.357196964442394,"y":0.6695897197162012,"z":-4.998320336944123}},"type":"POSITION"},{"content":{"spd":{"r":0.0,"x":-4.6715322810086946e-07,"y":5.735496984016208e-07,"z":0.09962489455938339}},"type":"VELOCITY"},{"content":{"frames":[{"sizeX":16,"sizeY":16,"startX":240,"startY":0}],"spriteName":"ball","textureName":"spritesheet"},"type":"DRAWABLE"},{"content":{"elasticity":0.98,"height":0.875,"mass":1.0,"volume":0.2,"width":0.875},"type":"BODY"}],"tags":["ACTIVE"]},{"components":[{"content":{"parent":200,"pos":{"r":6.038790782498747,"x":-13.478221191256448,"y":0.352741667375631,"z":2.810317161946646}},"type":"POSITION"}],"tags":["CAMERA","ACTIVE"]},{"components":[{"content":{"nameString":"Captain Lewis"},"type":"NAME"},{"content":{"parent":200,"pos":{"r":6.038790782498747,"x":-13.478221192401788,"y":0.3527416604686918,"z":0.00018356095641069498}},"type":"POSITION"},{"content":{"spd":{"r":0.0,"x":5.1887944607642567e-08,"y":3.1290875313061406e-07,"z":0.006052596960216761}},"type":"VELOCITY"},{"content":{"frames":[{"sizeX":16,"sizeY":16,"startX":256,"startY":0},{"sizeX":16,"sizeY":16,"startX":256,"startY":16},{"sizeX":16,"sizeY":16,"startX":256,"startY":32},{"sizeX":16,"sizeY":16,"startX":256,"startY":48},{"sizeX":16,"sizeY":16,"startX":256,"startY":64},{"sizeX":16,"sizeY":16,"startX":256,"startY":80},{"sizeX":16,"sizeY":16,"startX":272,"startY":0},{"sizeX":16,"sizeY":16,"startX":272,"startY":16},{"sizeX":16,"sizeY":16,"startX":272,"startY":32},{"sizeX":16,"sizeY":16,"startX":272,"startY":48},{"sizeX":16,"sizeY":16,"startX":272,"startY":64},{"sizeX":16,"sizeY":16,"startX":272,"startY":80}],"spriteName":"player3","textureName":"spritesheet"},"type":"DRAWABLE"},{"content":{"elasticity":0.1,"height":0.8,"mass":65.0,"volume":0.07,"width":0.8},"type":"BODY"},{"content":{"brain":null,"type":"astronaut"},"type":"BRAIN"}],"tags":["PLAYER","ACTIVE"]}]