{"CoM":{"r":0.0,"x":0.0,"y":0.0,"z":0.0},"children":[{"CoM":{"r":0.0,"x":0.0,"y":0.0,"z":0.0},"children":[{"CoM":{"r":0.0,"x":0.0,"y":0.0,"z":0.0},"children":[],"color":{"a":255,"b":200,"g":200,"r":200},"diameter":4879000.0,"generator":{"generator":{"diameter":4879000,"emptyBlockID":1,"liquidID":22072,"liquidLevel":0,"seed":2,"terrainPainter":{"emptyBlockID":1,"sections":[{"baseBlockID":97,"noiseCeiling":0.0001,"sectionWidth":200},{"baseBlockID":97,"noiseCeiling":1.0,"sectionWidth":100,"surfaceBlock":7}]}},"type":"terrainPainter"},"id":2,"interactables":null,"mass":3.285e+23,"name":"Mercury","position":{"r":0.0,"x":-31428332521.984154,"y":47488087024.05878,"z":0.0},"thrustSystem":{"containers":[{"ftContainers":{"containers":null,"index":-1},"fuelID":0},{"ftContainers":{"containers":null,"index":-1},"fuelID":1}],"thrusters":null},"type":"PLANET_ROCK","velocity":{"r":0.0,"x":1153998.206512731,"y":-1830954.780764619,"z":0.0}},{"CoM":{"r":0.0,"x":0.0,"y":0.0,"z":0.0},"children":[],"color":{"a":255,"b":0,"g":255,"r":255},"diameter":12102000.0,"generator":{"generator":{"diameter":12102000,"emptyBlockID":103,"liquidID":22072,"liquidLevel":0,"seed":3,"terrainPainter":{"emptyBlockID":103,"sections":[{"baseBlockID":98,"noiseCeiling":0.0001,"sectionWidth":200},{"baseBlockID":98,"noiseCeiling":1.0,"sectionWidth":100,"surfaceBlock":99}]}},"type":"terrainPainter"},"id":3,"interactables":null,"mass":4.8675e+24,"name":"Venus","position":{"r":0.0,"x":-18386358184.916916,"y":44690514968.20873,"z":0.0},"thrustSystem":{"containers":[{"ftContainers":{"containers":null,"index":-1},"fuelID":0},{"ftContainers":{"containers":null,"index":-1},"fuelID":1}],"thrusters":null},"type":"PLANET_ROCK","velocity":{"r":0.0,"x":747154.4079797136,"y":-2021950.9964662285,"z":0.0}},{"CoM":{"r":0.0,"x":0.0,"y":0.0,"z":0.0},"children":[{"CoM":{"r":0.0,"x":0.0,"y":0.0,"z":0.0},"children":[],"color":{"a":255,"b":200,"g":200,"r":200},"diameter":3474200.0,"generator":{"generator":{"diameter":3474200,"emptyBlockID":1,"liquidID":22072,"liquidLevel":0,"seed":10,"terrainPainter":{"emptyBlockID":1,"sections":[{"baseBlockID":97,"noiseCeiling":0.0001,"sectionWidth":200},{"baseBlockID":97,"noiseCeiling":1.0,"sectionWidth":100,"surfaceBlock":7}]}},"type":"terrainPainter"},"id":10,"interactables":null,"mass":7.342e+22,"name":"Selene","position":{"r":0.0,"x":4921006.336357038,"y":-238897998.1051227,"z":0.0},"thrustSystem":{"containers":[{"ftContainers":{"containers":null,"index":-1},"fuelID":0},{"ftContainers":{"containers":null,"index":-1},"fuelID":1}],"thrusters":null},"type":"SATELLITE_NATURAL","velocity":{"r":0.0,"x":55.601437884043406,"y":77133.14713565492,"z":0.0}},{"CoM":{"r":0.0,"x":2.0,"y":2.0,"z":0.0},"artificial_gravity":{"r":0.0,"x":0.0,"y":0.0,"z":-2.0},"children":[],"color":{"a":255,"b":255,"g":255,"r":255},"diameter":128.0,"generator":{"generator":{"name":"Roc"},"type":"prefab"},"id":200,"interactables":[{"interactable":{"positions":[{"r":0.0,"x":20.0,"y":14.0,"z":8.0},{"r":0.0,"x":20.0,"y":17.0,"z":8.0}],"thrustTarget":{"x":0.0,"y":0.0,"z":0.0}},"type":"NODE_CONTROLLER"},{"interactable":{"blocks":[{"block":{"baseID":115,"flip":false,"rotation":3,"save":true},"position":{"x":20,"y":14,"z":3}},{"block":{"baseID":125,"flip":false,"rotation":2,"save":true},"position":{"x":12,"y":13,"z":3}},{"block":{"baseID":125,"flip":false,"rotation":2,"save":true},"position":{"x":12,"y":13,"z":4}},{"block":{"baseID":125,"flip":false,"rotation":2,"save":true},"position":{"x":12,"y":13,"z":5}},{"block":{"baseID":125,"flip":false,"rotation":2,"save":true},"position":{"x":12,"y":13,"z":6}},{"block":{"baseID":123,"flip":false,"rotation":0,"save":true},"position":{"x":12,"y":14,"z":3}},{"block":{"baseID":123,"flip":false,"rotation":0,"save":true},"position":{"x":12,"y":14,"z":4}},{"block":{"baseID":123,"flip":false,"rotation":0,"save":true},"position":{"x":12,"y":14,"z":5}},{"block":{"baseID":123,"flip":false,"rotation":0,"save":true},"position":{"x":12,"y":14,"z":6}},{"block":{"baseID":123,"flip":false,"rotation":0,"save":true},"position":{"x":12,"y":15,"z":3}},{"block":{"baseID":123,"flip":false,"rotation":0,"save":true},"position":{"x":12,"y":15,"z":4}},{"block":{"baseID":123,"flip":false,"rotation":0,"save":true},"position":{"x":12,"y":15,"z":5}},{"block":{"baseID":123,"flip":false,"rotation":0,"save":true},"position":{"x":12,"y":15,"z":6}},{"block":{"baseID":123,"flip":false,"rotation":0,"save":true},"position":{"x":12,"y":16,"z":3}},{"block":{"baseID":123,"flip":false,"rotation":0,"save":true},"position":{"x":12,"y":16,"z":4}},{"block":{"baseID":123,"flip":false,"rotation":0,"save":true},"position":{"x":12,"y":16,"z":5}},{"block":{"baseID":123,"flip":false,"rotation":0,"save":true},"position":{"x":12,"y":16,"z":6}},{"block":{"baseID":123,"flip":false,"rotation":0,"save":true},"position":{"x":12,"y":17,"z":3}},{"block":{"baseID":123,"flip":false,"rotation":0,"save":true},"position":{"x":12,"y":17,"z":4}},{"block":{"baseID":123,"flip":false,"rotation":0,"save":true},"position":{"x":12,"y":17,"z":5}},{"block":{"baseID":123,"flip":false,"rotation":0,"save":true},"position":{"x":12,"y":17,"z":6}},{"block":{"baseID":125,"flip":false,"rotation":0,"save":true},"position":{"x":12,"y":18,"z":3}},{"block":{"baseID":125,"flip":false,"rotation":0,"save":true},"position":{"x":12,"y":18,"z":4}},{"block":{"baseID":125,"flip":false,"rotation":0,"save":true},"position":{"x":12,"y":18,"z":5}},{"block":{"baseID":125,"flip":false,"rotation":0,"save":true},"position":{"x":12,"y":18,"z":6}},{"block":{"baseID":96,"flip":false,"rotation":0,"save":true},"position":{"x":11,"y":14,"z":2}},{"block":{"baseID":96,"flip":false,"rotation":0,"save":true},"position":{"x":11,"y":15,"z":2}},{"block":{"baseID":96,"flip":false,"rotation":0,"save":true},"position":{"x":11,"y":16,"z":2}},{"block":{"baseID":96,"flip":false,"rotation":0,"save":true},"position":{"x":11,"y":17,"z":2}},{"block":{"baseID":96,"flip":false,"rotation":0,"save":true},"position":{"x":10,"y":14,"z":1}},{"block":{"baseID":96,"flip":false,"rotation":0,"save":true},"position":{"x":10,"y":15,"z":1}},{"block":{"baseID":96,"flip":false,"rotation":0,"save":true},"position":{"x":10,"y":16,"z":1}},{"block":{"baseID":96,"flip":false,"rotation":0,"save":true},"position":{"x":10,"y":17,"z":1}},{"block":{"baseID":96,"flip":false,"rotation":0,"save":true},"position":{"x":9,"y":14,"z":0}},{"block":{"baseID":96,"flip":false,"rotation":0,"save":true},"position":{"x":9,"y":15,"z":0}},{"block":{"baseID":96,"flip":false,"rotation":0,"save":true},"position":{"x":9,"y":16,"z":0}},{"block":{"baseID":96,"flip":false,"rotation":0,"save":true},"position":{"x":9,"y":17,"z":0}}],"positions":[{"r":0.0,"x":20.0,"y":14.0,"z":3.0}],"sfx":"sfx/door"},"type":"BLOCK_SWITCH"},{"interactable":{"blocks":[{"block":{"baseID":123,"flip":false,"rotation":1,"save":true},"position":{"x":15,"y":12,"z":8}}],"positions":[{"r":0.0,"x":15.0,"y":12.0,"z":8.0}],"sfx":"sfx/door"},"type":"BLOCK_SWITCH"},{"interactable":{"blocks":[{"block":{"baseID":123,"flip":false,"rotation":1,"save":true},"position":{"x":24,"y":15,"z":4}}],"positions":[{"r":0.0,"x":24.0,"y":15.0,"z":4.0}],"sfx":"sfx/door"},"type":"BLOCK_SWITCH"},{"interactable":{"blocks":[{"block":{"baseID":123,"flip":false,"rotation":1,"save":true},"position":{"x":27,"y":15,"z":4}}],"positions":[{"r":0.0,"x":27.0,"y":15.0,"z":4.0}],"sfx":"sfx/door"},"type":"BLOCK_SWITCH"},{"interactable":{"blocks":[{"block":{"baseID":123,"flip":false,"rotation":0,"save":true},"position":{"x":28,"y":14,"z":4}}],"positions":[{"r":0.0,"x":28.0,"y":14.0,"z":4.0}],"sfx":"sfx/door"},"type":"BLOCK_SWITCH"}],"mass":1000000.0,"name":"Roc","position":{"r":0.0,"x":446.0718646128366,"y":30020.999935508546,"z":281.00012779414925},"thrustSystem":{"containers":[{"ftContainers":{"containers":null,"index":0},"fuelID":0},{"ftContainers":{"containers":[{"capacity":500000.0,"content":500000.0,"fuelID":1,"position":{"x":32,"y":15,"z":4}},{"capacity":500000.0,"content":500000.0,"fuelID":1,"position":{"x":33,"y":15,"z":4}},{"capacity":500000.0,"content":500000.0,"fuelID":1,"position":{"x":34,"y":15,"z":4}},{"capacity":500000.0,"content":500000.0,"fuelID":1,"position":{"x":32,"y":16,"z":4}},{"capacity":500000.0,"content":500000.0,"fuelID":1,"position":{"x":33,"y":16,"z":4}},{"capacity":500000.0,"content":500000.0,"fuelID":1,"position":{"x":34,"y":16,"z":4}}],"index":5},"fuelID":1}],"thrusters":[{"agility":0.25,"blocks":[{"block":{"baseID":127,"flip":false,"rotation":0,"save":true},"position":{"x":17,"y":15,"z":0}}],"consumption":500.0,"current":0.0,"fuelID":1,"maxThrust":2000000.0,"position":{"x":17.0,"y":15.0,"z":1.0},"target":0.0,"thrustDirection":{"x":0.0,"y":0.0,"z":1.0}},{"agility":0.25,"blocks":[{"block":{"baseID":127,"flip":false,"rotation":0,"save":true},"position":{"x":18,"y":15,"z":0}}],"consumption":500.0,"current":0.0,"fuelID":1,"maxThrust":2000000.0,"position":{"x":18.0,"y":15.0,"z":1.0},"target":0.0,"thrustDirection":{"x":0.0,"y":0.0,"z":1.0}},{"agility":0.25,"blocks":[{"block":{"baseID":127,"flip":false,"rotation":0,"save":true},"position":{"x":17,"y":16,"z":0}}],"consumption":500.0,"current":0.0,"fuelID":1,"maxThrust":2000000.0,"position":{"x":17.0,"y":16.0,"z":1.0},"target":0.0,"thrustDirection":{"x":0.0,"y":0.0,"z":1.0}},{"agility":0.25,"blocks":[{"block":{"baseID":127,"flip":false,"rotation":0,"save":true},"position":{"x":18,"y":16,"z":0}}],"consumption":500.0,"current":0.0,"fuelID":1,"maxThrust":2000000.0,"position":{"x":18.0,"y":16.0,"z":1.0},"target":0.0,"thrustDirection":{"x":0.0,"y":0.0,"z":1.0}},{"agility":0.25,"blocks":[{"block":{"baseID":127,"flip":true,"rotation":2,"save":true},"position":{"x":28,"y":15,"z":1}}],"consumption":500.0,"current":0.0,"fuelID":1,"maxThrust":2000000.0,"position":{"x":28.0,"y":15.0,"z":2.0},"target":0.0,"thrustDirection":{"x":0.0,"y":0.0,"z":1.0}},{"agility":0.25,"blocks":[{"block":{"baseID":127,"flip":false,"rotation":0,"save":true},"position":{"x":29,"y":15,"z":1}}],"consumption":500.0,"current":0.0,"fuelID":1,"maxThrust":2000000.0,"position":{"x":29.0,"y":15.0,"z":2.0},"target":0.0,"thrustDirection":{"x":0.0,"y":0.0,"z":1.0}},{"agility":0.25,"blocks":[{"block":{"baseID":127,"flip":false,"rotation":0,"save":true},"position":{"x":28,"y":16,"z":1}}],"consumption":500.0,"current":0.0,"fuelID":1,"maxThrust":2000000.0,"position":{"x":28.0,"y":16.0,"z":2.0},"target":0.0,"thrustDirection":{"x":0.0,"y":0.0,"z":1.0}},{"agility":0.25,"blocks":[{"block":{"baseID":127,"flip":true,"rotation":2,"save":true},"position":{"x":29,"y":16,"z":1}}],"consumption":500.0,"current":0.0,"fuelID":1,"maxThrust":2000000.0,"position":{"x":29.0,"y":16.0,"z":2.0},"target":0.0,"thrustDirection":{"x":0.0,"y":0.0,"z":1.0}},{"agility":0.25,"blocks":[{"block":{"baseID":130,"flip":false,"rotation":3,"save":true},"position":{"x":28,"y":13,"z":2}}],"consumption":1000.0,"current":0.0,"fuelID":1,"maxThrust":4000000.0,"position":{"x":27.0,"y":13.0,"z":2.0},"target":0.0,"thrustDirection":{"x":-1.0,"y":0.0,"z":0.0}},{"agility":0.25,"blocks":[{"block":{"baseID":130,"flip":false,"rotation":3,"save":true},"position":{"x":28,"y":18,"z":2}}],"consumption":1000.0,"current":0.0,"fuelID":1,"maxThrust":4000000.0,"position":{"x":27.0,"y":18.0,"z":2.0},"target":0.0,"thrustDirection":{"x":-1.0,"y":0.0,"z":0.0}},{"agility":0.25,"blocks":[{"block":{"baseID":130,"flip":true,"rotation":2,"save":true},"position":{"x":19,"y":10,"z":4}}],"consumption":2000.0,"current":0.0,"fuelID":1,"maxThrust":8000000.0,"position":{"x":19.0,"y":11.0,"z":4.0},"target":0.0,"thrustDirection":{"x":0.0,"y":1.0,"z":0.0}},{"agility":0.25,"blocks":[{"block":{"baseID":130,"flip":false,"rotation":0,"save":true},"position":{"x":19,"y":21,"z":4}}],"consumption":2000.0,"current":0.0,"fuelID":1,"maxThrust":8000000.0,"position":{"x":19.0,"y":20.0,"z":4.0},"target":0.0,"thrustDirection":{"x":0.0,"y":-1.0,"z":0.0}},{"agility":0.25,"blocks":[{"block":{"baseID":89,"flip":false,"rotation":1,"save":true},"position":{"x":7,"y":15,"z":8}},{"block":{"baseID":89,"flip":false,"rotation":1,"save":true},"position":{"x":7,"y":16,"z":8}}],"consumption":2000.0,"current":0.0,"fuelID":1,"maxThrust":8000000.0,"position":{"x":10.0,"y":15.0,"z":8.0},"target":0.0,"thrustDirection":{"x":1.0,"y":0.0,"z":0.0}},{"agility":0.25,"blocks":[{"block":{"baseID":127,"flip":false,"rotation":0,"save":true},"position":{"x":24,"y":15,"z":8}}],"consumption":500.0,"current":0.0,"fuelID":1,"maxThrust":2000000.0,"position":{"x":24.0,"y":15.0,"z":7.0},"target":0.0,"thrustDirection":{"x":0.0,"y":0.0,"z":-1.0}},{"agility":0.25,"blocks":[{"block":{"baseID":127,"flip":false,"rotation":0,"save":true},"position":{"x":24,"y":16,"z":8}}],"consumption":500.0,"current":0.0,"fuelID":1,"maxThrust":2000000.0,"position":{"x":24.0,"y":16.0,"z":7.0},"target":0.0,"thrustDirection":{"x":0.0,"y":0.0,"z":-1.0}},{"agility":0.25,"blocks":[{"block":{"baseID":127,"flip":false,"rotation":0,"save":true},"position":{"x":13,"y":9,"z":9}}],"consumption":500.0,"current":0.0,"fuelID":1,"maxThrust":2000000.0,"position":{"x":13.0,"y":9.0,"z":8.0},"target":0.0,"thrustDirection":{"x":0.0,"y":0.0,"z":-1.0}},{"agility":0.25,"blocks":[{"block":{"baseID":127,"flip":false,"rotation":0,"save":true},"position":{"x":13,"y":22,"z":9}}],"consumption":500.0,"current":0.0,"fuelID":1,"maxThrust":2000000.0,"position":{"x":13.0,"y":22.0,"z":8.0},"target":0.0,"thrustDirection":{"x":0.0,"y":0.0,"z":-1.0}}]},"type":"SPACESHIP","velocity":{"r":0.0,"x":0.0,"y":0.0,"z":0.0}},{"CoM":{"r":0.0,"x":2.0,"y":2.0,"z":0.0},"children":[],"color":{"a":255,"b":0,"g":255,"r":255},"diameter":16.0,"generator":{"generator":{"name":"Sparrow"},"type":"prefab"},"id":201,"interactables":[{"interactable":{"positions":[{"r":0.0,"x":2.0,"y":1.0,"z":2.0}],"thrustTarget":{"x":0.0,"y":0.0,"z":0.0}},"type":"NODE_CONTROLLER"},{"interactable":{"blocks":[{"block":{"baseID":0,"flip":false,"rotation":0,"save":true},"position":{"x":2,"y":1,"z":3}}],"positions":[{"r":0.0,"x":2.0,"y":1.0,"z":3.0}],"sfx":"sfx/door"},"type":"BLOCK_SWITCH"}],"mass":10000.0,"name":"Sparrow","position":{"r":0.0,"x":461.40147719504836,"y":30034.00049348084,"z":283.0004953550755},"thrustSystem":{"containers":[{"ftContainers":{"containers":null,"index":0},"fuelID":0},{"ftContainers":{"containers":[{"capacity":50000.0,"content":50000.0,"fuelID":1,"position":{"x":1,"y":1,"z":2}},{"capacity":50000.0,"content":50000.0,"fuelID":1,"position":{"x":3,"y":1,"z":2}}],"index":1},"fuelID":1}],"thrusters":[{"agility":0.5,"blocks":[{"block":{"baseID":142,"flip":false,"rotation":0,"save":true},"position":{"x":2,"y":3,"z":2}}],"consumption":500.0,"current":0.0,"fuelID":1,"maxThrust":20000.0,"position":{"x":2.0,"y":2.0,"z":2.0},"target":0.0,"thrustDirection":{"x":0.0,"y":-1.0,"z":0.0}},{"agility":0.5,"blocks":[{"block":{"baseID":127,"flip":false,"rotation":0,"save":true},"position":{"x":2,"y":1,"z":0}}],"consumption":5000.0,"current":0.0,"fuelID":1,"maxThrust":200000.0,"position":{"x":2.0,"y":1.0,"z":1.0},"target":0.0,"thrustDirection":{"x":0.0,"y":0.0,"z":1.0}},{"agility":0.5,"blocks":[{"block":{"baseID":130,"flip":false,"rotation":3,"save":true},"position":{"x":1,"y":1,"z":0}}],"consumption":500.0,"current":0.0,"fuelID":1,"maxThrust":20000.0,"position":{"x":2.0,"y":1.0,"z":1.0},"target":0.0,"thrustDirection":{"x":1.0,"y":0.0,"z":0.0}},{"agility":0.5,"blocks":[{"block":{"baseID":130,"flip":false,"rotation":1,"save":true},"position":{"x":3,"y":1,"z":1}}],"consumption":500.0,"current":0.0,"fuelID":1,"maxThrust":20000.0,"position":{"x":2.0,"y":1.0,"z":1.0},"target":0.0,"thrustDirection":{"x":-1.0,"y":0.0,"z":0.0}},{"agility":0.5,"blocks":[{"block":{"baseID":130,"flip":false,"rotation":2,"save":true},"position":{"x":2,"y":0,"z":1}}],"consumption":500.0,"current":0.0,"fuelID":1,"maxThrust":20000.0,"position":{"x":2.0,"y":1.0,"z":1.0},"target":0.0,"thrustDirection":{"x":0.0,"y":1.0,"z":0.0}},{"agility":0.5,"blocks":null,"consumption":500.0,"current":0.0,"fuelID":1,"maxThrust":20000.0,"position":{"x":2.0,"y":1.0,"z":1.0},"target":0.0,"thrustDirection":{"x":0.0,"y":0.0,"z":-1.0}}]},"type":"SPACESHIP","velocity":{"r":0.0,"x":0.0,"y":0.0,"z":0.0}}],"color":{"a":255,"b":0,"g":255,"r":0},"diameter":12742000.0,"generator":{"generator":{"diameter":12742000,"emptyBlockID":2,"liquidID":3,"liquidLevel":240,"seed":4,"terrainPainter":{"emptyBlockID":2,"sections":[{"baseBlockID":6,"noiseCeiling":0.0001,"sectionWidth":60},{"baseBlockID":6,"noiseCeiling":0.2,"sectionWidth":60},{"baseBlockID":4,"noiseCeiling":0.4,"sectionWidth":60},{"baseBlockID":10,"noiseCeiling":0.48,"sectionWidth":60},{"baseBlockID":29,"noiseCeiling":0.5,"sectionWidth":5,"surfaceBlock":10},{"baseBlockID":4,"noiseCeiling":0.6,"sectionWidth":40,"surfaceBlock":5},{"baseBlockID":4,"noiseCeiling":0.65,"sectionWidth":10,"surfaceBlock":17},{"baseBlockID":98,"noiseCeiling":0.7,"sectionWidth":60,"surfaceBlock":6},{"baseBlockID":6,"noiseCeiling":0.75,"sectionWidth":40,"surfaceBlock":16},{"baseBlockID":107,"noiseCeiling":0.8,"sectionWidth":40,"surfaceBlock":16},{"baseBlockID":107,"noiseCeiling":1.0,"sectionWidth":10,"surfaceBlock":16}]}},"type":"terrainPainter"},"id":4,"interactables":null,"mass":5.97237e+24,"name":"Gaia","position":{"r":0.0,"x":6312237433.289658,"y":46777572215.6325,"z":0.0},"thrustSystem":{"containers":[{"ftContainers":{"containers":null,"index":-1},"fuelID":0},{"ftContainers":{"containers":null,"index":-1},"fuelID":1}],"thrusters":null},"type":"PLANET_ROCK","velocity":{"r":0.0,"x":-385288.5529722015,"y":-2149439.917922075,"z":0.0}},{"CoM":{"r":0.0,"x":0.0,"y":0.0,"z":0.0},"children":[],"color":{"a":255,"b":0,"g":0,"r":255},"diameter":6779000.0,"generator":{"generator":{"diameter":6779000,"emptyBlockID":2,"liquidID":3,"liquidLevel":0,"seed":5,"terrainPainter":{"emptyBlockID":2,"sections":[{"baseBlockID":98,"noiseCeiling":0.0001,"sectionWidth":200},{"baseBlockID":98,"noiseCeiling":1.0,"sectionWidth":100,"surfaceBlock":99}]}},"type":"terrainPainter"},"id":5,"interactables":null,"mass":6.4171e+23,"name":"Mars","position":{"r":0.0,"x":72288481913.21791,"y":50316912645.00196,"z":0.0},"thrustSystem":{"containers":[{"ftContainers":{"containers":null,"index":-1},"fuelID":0},{"ftContainers":{"containers":null,"index":-1},"fuelID":1}],"thrusters":null},"type":"PLANET_ROCK","velocity":{"r":0.0,"x":-1870815.9314966688,"y":-1226518.2315826525,"z":0.0}},{"CoM":{"r":0.0,"x":0.0,"y":0.0,"z":0.0},"children":[],"color":{"a":255,"b":66,"g":92,"r":111},"diameter":139820000.0,"generator":{"generator":{"diameter":139820000,"emptyBlockID":102,"liquidID":3,"liquidLevel":0,"seed":6,"terrainPainter":{"emptyBlockID":102,"sections":[{"baseBlockID":102,"noiseCeiling":0.0001,"sectionWidth":200},{"baseBlockID":100,"noiseCeiling":0.0002,"sectionWidth":100},{"baseBlockID":102,"noiseCeiling":1.0,"sectionWidth":1}]}},"type":"terrainPainter"},"id":6,"interactables":null,"mass":1.898e+27,"name":"Jupiter","position":{"r":0.0,"x":619419892400.3386,"y":37093198127.52553,"z":0.0},"thrustSystem":{"containers":[{"ftContainers":{"containers":null,"index":-1},"fuelID":0},{"ftContainers":{"containers":null,"index":-1},"fuelID":1}],"thrusters":null},"type":"PLANET_GAS","velocity":{"r":0.0,"x":-2254561.0242707147,"y":-118583.48394210165,"z":0.0}},{"CoM":{"r":0.0,"x":0.0,"y":0.0,"z":0.0},"children":[],"color":{"a":255,"b":66,"g":92,"r":111},"diameter":116460000.0,"generator":{"generator":{"diameter":116460000,"emptyBlockID":102,"liquidID":3,"liquidLevel":0,"seed":7,"terrainPainter":{"emptyBlockID":102,"sections":[{"baseBlockID":102,"noiseCeiling":0.0001,"sectionWidth":200},{"baseBlockID":100,"noiseCeiling":0.0002,"sectionWidth":100},{"baseBlockID":102,"noiseCeiling":1.0,"sectionWidth":1}]}},"type":"terrainPainter"},"id":7,"interactables":null,"mass":5.683e+26,"name":"Saturn","position":{"r":0.0,"x":1274335005444.9763,"y":28595516641.22461,"z":0.0},"thrustSystem":{"containers":[{"ftContainers":{"containers":null,"index":-1},"fuelID":0},{"ftContainers":{"containers":null,"index":-1},"fuelID":1}],"thrusters":null},"type":"PLANET_GAS","velocity":{"r":0.0,"x":-2257913.517487186,"y":-39777.32146347947,"z":0.0}},{"CoM":{"r":0.0,"x":0.0,"y":0.0,"z":0.0},"children":[],"color":{"a":255,"b":255,"g":0,"r":0},"diameter":50724000.0,"generator":{"generator":{"diameter":50724000,"emptyBlockID":101,"liquidID":3,"liquidLevel":0,"seed":8,"terrainPainter":{"emptyBlockID":101,"sections":[{"baseBlockID":106,"noiseCeiling":0.0001,"sectionWidth":200},{"baseBlockID":101,"noiseCeiling":0.0002,"sectionWidth":100},{"baseBlockID":101,"noiseCeiling":1.0,"sectionWidth":50}]}},"type":"terrainPainter"},"id":8,"interactables":null,"mass":8.681e+25,"name":"Uranus","position":{"r":0.0,"x":2713198025956.9043,"y":20537742652.459347,"z":0.0},"thrustSystem":{"containers":[{"ftContainers":{"containers":null,"index":-1},"fuelID":0},{"ftContainers":{"containers":null,"index":-1},"fuelID":1}],"thrusters":null},"type":"PLANET_GAS","velocity":{"r":0.0,"x":-2258400.7776295985,"y":-9896.120268479472,"z":0.0}},{"CoM":{"r":0.0,"x":0.0,"y":0.0,"z":0.0},"children":[],"color":{"a":255,"b":255,"g":0,"r":0},"diameter":49244000.0,"generator":{"generator":{"diameter":49244000,"emptyBlockID":101,"liquidID":3,"liquidLevel":0,"seed":9,"terrainPainter":{"emptyBlockID":101,"sections":[{"baseBlockID":106,"noiseCeiling":0.0001,"sectionWidth":200},{"baseBlockID":101,"noiseCeiling":0.0002,"sectionWidth":100},{"baseBlockID":101,"noiseCeiling":1.0,"sectionWidth":50}]}},"type":"terrainPainter"},"id":9,"interactables":null,"mass":1.0239999999999999e+26,"name":"Neptune","position":{"r":0.0,"x":4339197332575.529,"y":16526740569.48503,"z":0.0},"thrustSystem":{"containers":[{"ftContainers":{"containers":null,"index":-1},"fuelID":0},{"ftContainers":{"containers":null,"index":-1},"fuelID":1}],"thrusters":null},"type":"PLANET_GAS","velocity":{"r":0.0,"x":-2258447.5526894517,"y":-2972.5462578647025,"z":0.0}}],"color":{"a":255,"b":0,"g":127,"r":255},"diameter":1392684000.0,"generator":{"generator":{"diameter":1392684000,"emptyBlockID":1,"liquidID":3,"liquidLevel":0,"seed":1,"terrainPainter":{"emptyBlockID":1,"sections":[{"baseBlockID":104,"noiseCeiling":0.0001,"sectionWidth":400},{"baseBlockID":102,"noiseCeiling":0.0002,"sectionWidth":100},{"baseBlockID":0,"noiseCeiling":1.0,"sectionWidth":1}]}},"type":"terrainPainter"},"id":1,"interactables":null,"mass":1.9885e+30,"name":"Sun","position":{"r":0.0,"x":2.5543362211650136e+20,"y":678532079956.7466,"z":0.0},"thrustSystem":{"containers":[{"ftContainers":{"containers":null,"index":-1},"fuelID":0},{"ftContainers":{"containers":null,"index":-1},"fuelID":1}],"thrusters":null},"type":"STAR","velocity":{"r":0.0,"x":-9148361816.258268,"y":219976.25378150528,"z":0.0}}],"color":{"a":255,"b":255,"g":0,"r":255},"diameter":44000000000.0,"generator":{"generator":{"diameter":1050327040,"emptyBlockID":0,"liquidID":3,"liquidLevel":0,"seed":0,"terrainPainter":{"emptyBlockID":0,"sections":[{"baseBlockID":106,"noiseCeiling":0.0001,"sectionWidth":5},{"baseBlockID":0,"noiseCeiling":1.0,"sectionWidth":1}]}},"type":"terrainPainter"},"id":0,"interactables":null,"mass":8.04e+36,"name":"Saggitarius A*","position":{"r":0.0,"x":0.0,"y":0.0,"z":0.0},"thrustSystem":{"containers":[{"ftContainers":{"containers":null,"index":-1},"fuelID":0},{"ftContainers":{"containers":null,"index":-1},"fuelID":1}],"thrusters":null},"type":"BLACK_HOLE","velocity":{"r":0.0,"x":0.0,"y":0.0,"z":0.0}}